{
  "seq": 429,
  "type": "AGENT_RESPONSE",
  "timestamp": "2026-01-04T20:07:30.831Z",
  "data": {
    "priority": "stability",
    "action": "state.summary",
    "reason": "Stability feeling: drifting (V=0.1600)",
    "constitutionalCheck": "passed",
    "energyBefore": 0.485,
    "energyAfter": 0.482,
    "executed": true,
    "result": {
      "success": true,
      "message": "Summary generated",
      "effects": {
        "status": "nominal",
        "energy": 0.485,
        "events": 424,
        "sessions": 43,
        "coupled": false
      }
    }
  },
  "prev_hash": "0429ab1821d33cd4632543ee783a427d14f08471633e74694bde0be8018db7ec",
  "hash": "bc143accc6a38682f5b7df552b5e7ecf4c72be683afde30ea7b91eadb0c52a58"
}